pyCGA/__init__.py
pyCGA/commons.py
pyCGA/exceptions.py
pyCGA/opencgaconfig.py
pyCGA/opencgarestclients.py
pyCGA/retry.py
pyCGA/tests.py
pyCGA/Utils/AvroSchema.py
pyCGA/Utils/MockOpenCGA.py
pyCGA/Utils/__init__.py
pyCGA/Utils/decorators.py
pyCGA-1.3.0.dist-info/DESCRIPTION.rst
pyCGA-1.3.0.dist-info/METADATA
pyCGA-1.3.0.dist-info/RECORD
pyCGA-1.3.0.dist-info/WHEEL
pyCGA-1.3.0.dist-info/metadata.json
pyCGA-1.3.0.dist-info/top_level.txt
