Metadata-Version: 2.0
Name: pyCGA
Version: 1.3.0
Summary: A REST client for OpenCGA web services
Home-page: https://github.com/opencb/opencga/tree/develop/opencga-client/src/main/python
Author: antonior,dapregi,ernesto-ocampo
Author-email: antonio.rueda-martin@genomicsengland.co.uk,daniel.perez-gil@genomicsengland.co.uk,kenan.mcgrath@genomicsengland.co.uk
License: Apache Software License
Keywords: opencb opencga bioinformatics genomic database
Platform: UNKNOWN
Requires-Dist: PyYAML
Requires-Dist: avro (==1.7.7)
Requires-Dist: pathlib (>=1.0.1)
Requires-Dist: pip (>=7.1.2)
Requires-Dist: requests (>=2.7)
Requires-Dist: requests-toolbelt (>=0.7.0)
